{
    "title": "RBI hikes repo rate: Check out our coverage of central bank's policy review",
    "link": "https://www.business-standard.com/article/finance/rbi-hikes-repo-rate-full-coverage-on-every-aspect-of-latest-rbi-policy-review-118060700447_1.html",
    "pubDate": "Thu, 07 Jun 2018 14:42:00 +0530",
    "content": "From finance ministry's reaction to experts' opinion, read all our articles on RBI's latest monetary policy meet",
    "contentSnippet": "From finance ministry's reaction to experts' opinion, read all our articles on RBI's latest monetary policy meet",
    "guid": "https://www.business-standard.com/article/finance/rbi-hikes-repo-rate-full-coverage-on-every-aspect-of-latest-rbi-policy-review-118060700447_1.html",
    "isoDate": "2018-06-07T09:12:00.000Z",
    "sentiment": {
        "score": 0,
        "comparative": 0,
        "tokens": [
            "rbi",
            "hikes",
            "repo",
            "rate",
            "check",
            "out",
            "our",
            "coverage",
            "of",
            "central",
            "bank's",
            "policy",
            "review"
        ],
        "words": [],
        "positive": [],
        "negative": []
    },
    "article": {},
    "adjectives": [
        "monetary",
        "latest",
        "central",
        "meet"
    ],
    "nouns": [
        "bank",
        "rate",
        "Check",
        "finance",
        "latest",
        "RBI",
        "central",
        "ministry",
        "policy",
        "coverage",
        "review",
        "reaction",
        "read",
        "opinion",
        "meet"
    ],
    "verbs": [
        "bank",
        "rate",
        "Check",
        "finance",
        "review",
        "read",
        "meet"
    ]
}