{
    "title": "Bank of India ups MCLR by 0.10% from June 10 for various tenors",
    "link": "https://timesofindia.indiatimes.com/business/india-business/bank-of-india-ups-mclr-by-0-10-from-jun-10-for-various-tenors/articleshow/64505949.cms",
    "pubDate": "Fri, 08 Jun 2018 07:57:30 GMT",
    "content": "<a href=\"https://timesofindia.indiatimes.com/business/india-business/bank-of-india-ups-mclr-by-0-10-from-jun-10-for-various-tenors/articleshow/64505949.cms\"><img border=\"0\" hspace=\"10\" align=\"left\" style=\"margin-top:3px;margin-right:5px;\" src=\"https://timesofindia.indiatimes.com/photo/64505949.cms\" /></a>New Delhi, Jun 8 () Following peers, state-owned Bank of India has hiked lending rates based on MCLR by 0.10 per cent for various tenors.  The bank has increased MCLR rates by 10 bps (or 0.10 per cent) for various tenors, it said in a statement.",
    "contentSnippet": "New Delhi, Jun 8 () Following peers, state-owned Bank of India has hiked lending rates based on MCLR by 0.10 per cent for various tenors.  The bank has increased MCLR rates by 10 bps (or 0.10 per cent) for various tenors, it said in a statement.",
    "guid": "https://timesofindia.indiatimes.com/business/india-business/bank-of-india-ups-mclr-by-0-10-from-jun-10-for-various-tenors/articleshow/64505949.cms",
    "isoDate": "2018-06-08T07:57:30.000Z",
    "sentiment": {
        "score": 0,
        "comparative": 0,
        "tokens": [
            "bank",
            "of",
            "india",
            "ups",
            "mclr",
            "by",
            "010",
            "from",
            "june",
            "10",
            "for",
            "various",
            "tenors"
        ],
        "words": [],
        "positive": [],
        "negative": []
    },
    "article": {
        "title": "Bank of India ups MCLR by 0.10% from June 10 for various tenors",
        "content": "<section class=\"title_section clearfix\"><meta itemprop=\"headline\" content=\"Bank of India ups MCLR by 0.10% from June 10 for various tenors\"><p>New Delhi, Jun 8 () Following peers, state-owned Bank of India has hiked lending rates based on MCLR by 0.10 per cent for various tenors.  The bank has increased MCLR rates by 10 bps (or 0.10 per cent) for various tenors, it said in a statement.</p></section>"
    },
    "adjectives": [
        "increased",
        "10",
        "left",
        "top",
        "right",
        "various",
        "New",
        "Following",
        "owned",
        "based"
    ],
    "nouns": [
        "rates",
        "state",
        "statement",
        "India",
        "india",
        "business",
        "border",
        "10",
        "left",
        "style",
        "margin",
        "top",
        "right",
        "photo",
        "bps",
        "Bank",
        "bank",
        "June",
        "Delhi",
        "Following",
        "lending",
        "cent"
    ],
    "verbs": [
        "state",
        "border",
        "align",
        "style",
        "top",
        "right",
        "Bank",
        "bank"
    ]
}