{
    "title": "Cautiously optimistic on India; eyeing earnings revival: Sanger",
    "link": "http://www.moneycontrol.com/news/fii-view/cautiously-optimisticindia-eyeing-earnings-revival-sanger_7574941.html",
    "pubDate": "Wed, 05 Oct 2016 09:00:17 +0530",
    "content": "<img src=\"http://www.moneycontrol.com/news_image_files/2016/a/arvind-sanger-200-19116.jpg\" alt=\"Arvind Sanger \" title=\"Arvind Sanger \" border=\"0\" width=\"75\" height=\"75\" align=\" left\" hspace=\"5\"/> Global liquidity tailwinds are unlikely to get any better from now and that makes Arvind Sanger, Managing Partner at Geosphere Capital Management “cautiously optimistic” on the Indian markets.",
    "contentSnippet": "Global liquidity tailwinds are unlikely to get any better from now and that makes Arvind Sanger, Managing Partner at Geosphere Capital Management “cautiously optimistic” on the Indian markets.",
    "guid": "http://www.moneycontrol.com/news/fii-view/cautiously-optimisticindia-eyeing-earnings-revival-sanger_7574941.html",
    "isoDate": "2016-10-05T03:30:17.000Z",
    "sentiment": {
        "score": 2,
        "comparative": 0.25,
        "tokens": [
            "cautiously",
            "optimistic",
            "on",
            "india",
            "eyeing",
            "earnings",
            "revival",
            "sanger"
        ],
        "words": [
            "optimistic"
        ],
        "positive": [
            "optimistic"
        ],
        "negative": []
    },
    "article": {},
    "adjectives": [
        "Global",
        "75",
        "left",
        "optimistic",
        "Indian",
        "better",
        "Capital",
        "200",
        "unlikely"
    ],
    "nouns": [
        "http",
        "www",
        "alt",
        "title",
        "border",
        "width",
        "height",
        "left",
        "liquidity",
        "India",
        "Indian",
        "earnings",
        "revival",
        "Sanger",
        "sanger",
        "better",
        "Management",
        "Partner",
        "Capital",
        "Geosphere"
    ],
    "verbs": [
        "title",
        "border",
        "align",
        "better",
        "Partner"
    ]
}